pypcd/__init__.py
pypcd/nea_pc_format.py
pypcd/numpy_pc2.py
pypcd/pdutil.py
pypcd/pypcd.py
pypcd/sautil.py
pypcd-0.1.1.dist-info/DESCRIPTION.rst
pypcd-0.1.1.dist-info/METADATA
pypcd-0.1.1.dist-info/RECORD
pypcd-0.1.1.dist-info/WHEEL
pypcd-0.1.1.dist-info/metadata.json
pypcd-0.1.1.dist-info/top_level.txt
